malloc_tracer/__init__.py
malloc_tracer/tracer.py
malloc_tracer/version.py
malloc_tracer-1.6.0.dist-info/METADATA
malloc_tracer-1.6.0.dist-info/RECORD
malloc_tracer-1.6.0.dist-info/WHEEL
malloc_tracer-1.6.0.dist-info/top_level.txt
