Metadata-Version: 2.1
Name: malloc-tracer
Version: 1.6.0
Summary: This is a debugging tool for tracing malloc that occurs inside a function or class.
Home-page: https://github.com/Hasenpfote/malloc_tracer
Author: Hasenpfote
Author-email: Hasenpfote36@gmail.com
License: UNKNOWN
Keywords: debug,debugging-tool,tracemalloc
Platform: UNKNOWN
Classifier: Programming Language :: Python
Classifier: Programming Language :: Python :: 3
Classifier: Programming Language :: Python :: 3.4
Classifier: Programming Language :: Python :: 3.5
Classifier: Programming Language :: Python :: 3.6
Classifier: Programming Language :: Python :: 3.7
Classifier: License :: OSI Approved :: MIT License
Classifier: Operating System :: OS Independent
Classifier: Development Status :: 5 - Production/Stable
Classifier: Environment :: Other Environment
Classifier: Intended Audience :: Developers
Classifier: Topic :: Software Development
Classifier: Topic :: Utilities
Requires-Python: >=3.4
